nonebot_plugin_og/__init__.py
nonebot_plugin_og/utils.py
nonebot_plugin_og-0.3.0.dist-info/LICENSE
nonebot_plugin_og-0.3.0.dist-info/METADATA
nonebot_plugin_og-0.3.0.dist-info/WHEEL
nonebot_plugin_og-0.3.0.dist-info/RECORD
