Metadata-Version: 2.1
Name: nonebot-plugin-og
Version: 0.3.0
Summary: 检测链接并发送网站简介及预览图
License: MIT
Author: mute.
Author-email: mute231010@gmail.com
Requires-Python: >=3.10,<4.0
Classifier: License :: OSI Approved :: MIT License
Classifier: Programming Language :: Python :: 3
Classifier: Programming Language :: Python :: 3.10
Classifier: Programming Language :: Python :: 3.11
Requires-Dist: httpx (>=0.24.0,<0.25.0)
Requires-Dist: nonebot-adapter-onebot (>=2.2.3,<3.0.0)
Requires-Dist: nonebot2 (>=2.0.0rc4,<3.0.0)
Requires-Dist: pyquery (>=2.0.0,<3.0.0)
